sakshi_ocr.py
sakshi_ocr-0.2.0.dist-info/METADATA
sakshi_ocr-0.2.0.dist-info/WHEEL
sakshi_ocr-0.2.0.dist-info/top_level.txt
sakshi_ocr-0.2.0.dist-info/RECORD
