Metadata-Version: 2.2
Name: sakshi_ocr
Version: 0.2.0
Summary: A UNKNOWN sakshi_ocr
Home-page: https://github.com/NONE/sakshi_ocr_package
Author: sameer banchhor
Author-email: slimshadow.work@gmail.com
Classifier: Programming Language :: Python :: 3
Classifier: Operating System :: OS Independent
Dynamic: author
Dynamic: author-email
Dynamic: classifier
Dynamic: home-page
Dynamic: summary
